curious_me/__init__.py
curious_me/curious.py
curious_me/rag.py
curious_me/research_papers/.gitkeep
curious_me/searcher.py
curious_me/vector_store.py
curious_me-0.1.1.dist-info/LICENSE
curious_me-0.1.1.dist-info/METADATA
curious_me-0.1.1.dist-info/WHEEL
curious_me-0.1.1.dist-info/RECORD
