Metadata-Version: 2.1
Name: curious-me
Version: 0.1.1
Summary: Small project for aiding in research and development
Author: Ankit Kumar Pandey
Author-email: itsankitkp@gmail.com
Requires-Python: >=3.11,<4.0
Classifier: Programming Language :: Python :: 3
Classifier: Programming Language :: Python :: 3.11
Classifier: Programming Language :: Python :: 3.12
Classifier: Programming Language :: Python :: 3.13
Requires-Dist: arxiv (>=2.1.3,<3.0.0)
Requires-Dist: black (>=24.10.0,<25.0.0)
Requires-Dist: faiss-cpu (>=1.9.0.post1,<2.0.0)
Requires-Dist: ipython (>=8.31.0,<9.0.0)
Requires-Dist: ipywidgets (>=8.1.5,<9.0.0)
Requires-Dist: langchain (>=0.3.13,<0.4.0)
Requires-Dist: langchain-community (>=0.3.13,<0.4.0)
Requires-Dist: langchain-huggingface (>=0.1.2,<0.2.0)
Requires-Dist: langchain-openai (>=0.2.14,<0.3.0)
Requires-Dist: notebook (>=7.3.2,<8.0.0)
Requires-Dist: openai (>=1.58.1,<2.0.0)
Requires-Dist: pymupdf (>=1.25.1,<2.0.0)
Requires-Dist: sentence-transformers (>=3.3.1,<4.0.0)
Requires-Dist: torch (>=2.5.1,<3.0.0)
Requires-Dist: torchvision (>=0.20.1,<0.21.0)
Requires-Dist: tqdm (>=4.67.1,<5.0.0)
